star3d/__init__.py
star3d/example.py
star3d/utils_3Dsegmentation.py
star3d-0.0.1.dist-info/LICENSE.md
star3d-0.0.1.dist-info/METADATA
star3d-0.0.1.dist-info/WHEEL
star3d-0.0.1.dist-info/top_level.txt
star3d-0.0.1.dist-info/RECORD
